Metadata-Version: 2.4
Name: mcp-server-ssh-exec
Version: 0.1.0
Summary: Execute commands remotely through an ssh connection
Author-email: Jarad DeLorenzo <jaradd@gmail.com>
Requires-Python: >=3.12
Requires-Dist: mcp>=1.6.0
Requires-Dist: paramiko>=3.4.0
